xltojson/__init__.py
xltojson/xltojson1.py
xltojson_converter-1.0.0.dist-info/METADATA
xltojson_converter-1.0.0.dist-info/WHEEL
xltojson_converter-1.0.0.dist-info/entry_points.txt
xltojson_converter-1.0.0.dist-info/top_level.txt
xltojson_converter-1.0.0.dist-info/RECORD
