Metadata-Version: 2.1
Name: xltojson-converter
Version: 1.0.0
Summary: A utility to convert Excel files to JSON
Home-page: https://github.com/yourusername/xltojson
Author: Mahesh
Author-email: maheshyamana123@gmail.com
License: UNKNOWN
Platform: UNKNOWN
Classifier: Programming Language :: Python :: 3
Classifier: License :: OSI Approved :: MIT License
Classifier: Operating System :: OS Independent
Requires-Python: >=3.6
Requires-Dist: openpyxl
